CHANGES
LICENSE
MANIFEST.in
README.rst
osm.proto
setup.py
imposm/__init__.py
imposm.parser.egg-info/PKG-INFO
imposm.parser.egg-info/SOURCES.txt
imposm.parser.egg-info/dependency_links.txt
imposm.parser.egg-info/namespace_packages.txt
imposm.parser.egg-info/top_level.txt
imposm/parser/__init__.py
imposm/parser/simple.py
imposm/parser/util.py
imposm/parser/pbf/__init__.py
imposm/parser/pbf/multiproc.py
imposm/parser/pbf/osm.cc
imposm/parser/pbf/parser.py
imposm/parser/test/__init__.py
imposm/parser/test/test.osm
imposm/parser/test/test.osm.bz2
imposm/parser/test/test.pbf
imposm/parser/test/test_simple_parser.py
imposm/parser/xml/__init__.py
imposm/parser/xml/multiproc.py
imposm/parser/xml/parser.py
imposm/parser/xml/util.py