Metadata-Version: 1.0
Name: imposm.parser
Version: 1.0.5
Summary: Fast and easy OpenStreetMap XML/PBF parser.
Home-page: http://imposm.org/docs/imposm.parser/latest/
Author: Oliver Tonnhofer
Author-email: olt@omniscale.de
License: Apache Software License 2.0
Platform: UNKNOWN
Classifier: Development Status :: 4 - Beta
Classifier: License :: OSI Approved :: Apache Software License
Classifier: Operating System :: OS Independent
Classifier: Programming Language :: C
Classifier: Programming Language :: C++
Classifier: Programming Language :: Python :: 2.5
Classifier: Programming Language :: Python :: 2.6
Classifier: Programming Language :: Python :: 2.7
Classifier: Topic :: Software Development :: Libraries
Classifier: Topic :: Scientific/Engineering :: GIS
